{
  "id": "l-cn-bx-u8-4",
  "subj": "cn",
  "title": "阿房宫赋 精读——借古讽今与赋体铺陈",
  "sources": [
    "来源：金圣叹《金圣叹批才子古文》评《阿房宫赋》「穷其极丽，至矣尽矣！却是一篇最清出的文字」；元·祝尧《古赋辨体》称「至杜牧之《阿房宫赋》，古今脍炙」。",
    "来源：教学实录（瑞文网 ruiwen.com）——赋「铺事写志」（托物言志）：前半铺陈宫殿—美人—珍宝，后半议论秦亡教训，劝诫唐敬宗勿蹈覆辙。"
  ],
  "photo": "色块兜底",
  "audit": "PASS",
  "renderer": "tools/_render_l-cn-bx-u8-4.py",
  "note": "9页学生版（封面/学习目标/背景与权威调研/重点/方法/难点/板书精华/作业/单元小结）；每次课均经 WebSearch 核实权威来源并标注出处；本批课题（古代说理文、走近细胞/组成细胞的分子）无契合自由授权真实照片，按规范§2.3 学科色块兜底并在背景页标注「本课件未使用无关配图」；四层审计（文本口吻/遮罩/版面溢出/越界）全 PASS。"
}